nigeria_states_lgas/__init__.py
nigeria_states_lgas/cli.py
nigeria_states_lgas/utils.py
nigeria_states_lgas/data/nigeria_lgas.csv
nigeria_states_lgas/data/nigeria_lgas.json
nigeria_states_lgas/data/nigeria_states.csv
nigeria_states_lgas/data/nigeria_states.json
nigeria_states_lgas/data/nigeria_states_and_lgas.csv
nigeria_states_lgas/data/nigeria_states_and_lgas.json
nigeria_states_lgas/data/nigeria_states_and_lgas.sql
nigeria_states_lgas-1.0.6.dist-info/licenses/LICENSE
tests/test_utils.py
nigeria_states_lgas-1.0.6.dist-info/METADATA
nigeria_states_lgas-1.0.6.dist-info/WHEEL
nigeria_states_lgas-1.0.6.dist-info/top_level.txt
nigeria_states_lgas-1.0.6.dist-info/RECORD
