Metadata-Version: 2.4
Name: nigeria-states-lgas
Version: 1.0.6
Summary: Dataset of Nigerian states and local government areas (LGAs)
Home-page: https://github.com/aetechlabs/nigeria-states-lgas-py
Author: AETech Research Labs
Author-email: info@aetechlabs.com
License: MIT
Keywords: nigeria,states,lgas,geodata
Requires-Python: >=3.7
License-File: LICENSE
Dynamic: author
Dynamic: author-email
Dynamic: home-page
Dynamic: license-file
Dynamic: requires-python
